README.md
setup.py
Politibot/__init__.py
Politibot/ApiTools/Pagination.py
Politibot/ApiTools/QueryString.py
Politibot/ApiTools/ResultSet.py
Politibot/ApiTools/__init__.py
Politibot/ConnAssembly/ConnAssembly.py
Politibot/ConnAssembly/__init__.py
Politibot/Fec/Fec.py
Politibot/Fec/__init__.py
Politibot/ProPublica/CampaignFinance.py
Politibot/ProPublica/Congress.py
Politibot/ProPublica/Pagination.py
Politibot/ProPublica/ProPublicaApi.py
Politibot/ProPublica/__init__.py
politibot.egg-info/PKG-INFO
politibot.egg-info/SOURCES.txt
politibot.egg-info/dependency_links.txt
politibot.egg-info/requires.txt
politibot.egg-info/top_level.txt