Metadata-Version: 1.0
Name: politibot
Version: 0.0.0
Summary: Tools for pulling data from multiple political and legislative APIs
Home-page: UNKNOWN
Author: Jake Kara
Author-email: jake@jakekara.com
License: GPL-3
Platform: UNKNOWN
